
14. Smile in the mirror
#advanced

Écrire un programme qui imprime l'alphabet ASCII, dans l'ordre inverse, en alternant minuscules et majuscules
(z en minuscule et Y en majuscule) , non suivi d'une nouvelle ligne.

Vous ne pouvez utiliser qu'une seule fonction d'impression avec un format de chaîne
Vous ne pouvez utiliser qu'une seule boucle dans votre code
Vous n'êtes pas autorisé à stocker des caractères dans une variable
Vous n'êtes pas autorisé à importer un module


Write a program that prints the ASCII alphabet, in reverse order, alternating lowercase and uppercase 
(z in lowercase and Y in uppercase) , not followed by a new line.

You can only use one print function with string format
You can only use one loop in your code
You are not allowed to store characters in a variable
You are not allowed to import any module
guillaume@ubuntu:~/0x01$ ./100-print_tebahpla.py
zYxWvUtSrQpOnMlKjIhGfEdCbAguillaume@ubuntu:~/0x01$
Repo:

GitHub repository: alx-higher_level_programming
Directory: 0x01-python-if_else_loops_functions
File: 100-print_tebahpla.py
  
+++++++++++++++++++++++++++++++++++++++++++++++++++++++++++++++++++++++++++++++++++++++++++++++++++++++++++++++++++

15. Remove at position
#advanced
Écrivez une fonction qui crée une copie de la chaîne, en supprimant le caractère à la position n (pas à la manière Python,
l'"indice de tableau C").

Prototype : def remove_char_at(str, n) :
Vous n'êtes pas autorisé à importer un module


Write a function that creates a copy of the string, removing the character at the position n (not the Python way, 
the “C array index”).

Prototype: def remove_char_at(str, n):
You are not allowed to import any module
You don’t need to understand __import__

guillaume@ubuntu:~/0x01$ cat 101-main.py
#!/usr/bin/env python3
remove_char_at = __import__('101-remove_char_at').remove_char_at

print(remove_char_at("Best School", 3))
print(remove_char_at("Chicago", 2))
print(remove_char_at("C is fun!", 0))
print(remove_char_at("School", 10))
print(remove_char_at("Python", -2))

guillaume@ubuntu:~/0x01$ ./101-main.py
Bes School
Chcago
 is fun!
School
Python
guillaume@ubuntu:~/0x01$ 
Repo:

GitHub repository: alx-higher_level_programming
Directory: 0x01-python-if_else_loops_functions
File: 101-remove_char_at.py
  
++++++++++++++++++++++++++++++++++++++++++++++++++++++++++++++++++++++++++++++++++++++++++++++++++++++++++++++++++++++++

16. ByteCode -> Python #2
#advanced
Write the Python function def magic_calculation(a, b, c): that does exactly the same as the following Python bytecode:

  3           0 LOAD_FAST                0 (a)
              3 LOAD_FAST                1 (b)
              6 COMPARE_OP               0 (<)
              9 POP_JUMP_IF_FALSE       16

  4          12 LOAD_FAST                2 (c)
             15 RETURN_VALUE

  5     >>   16 LOAD_FAST                2 (c)
             19 LOAD_FAST                1 (b)
             22 COMPARE_OP               4 (>)
             25 POP_JUMP_IF_FALSE       36

  6          28 LOAD_FAST                0 (a)
             31 LOAD_FAST                1 (b)
             34 BINARY_ADD
             35 RETURN_VALUE

  7     >>   36 LOAD_FAST                0 (a)
             39 LOAD_FAST                1 (b)
             42 BINARY_MULTIPLY
             43 LOAD_FAST                2 (c)
             46 BINARY_SUBTRACT
             47 RETURN_VALUE
tips - ByteCode

Repo:

GitHub repository: alx-higher_level_programming
Directory: 0x01-python-if_else_loops_functions
File: 102-magic_calculation.py