
12. Fizz Buzz
mandatory
Écrivez une fonction qui imprime les nombres de 1 à 100 séparés par un espace.

Pour les multiples de trois, imprimez Fizz au lieu du nombre et pour les multiples de cinq, imprimez Buzz.
Pour les nombres qui sont des multiples de trois et de cinq, imprimez FizzBuzz.
Prototype : def fizzbuzz() :
Chaque élément doit être suivi d'un espace
Vous n'êtes pas autorisé à importer un module


Write a function that prints the numbers from 1 to 100 separated by a space.

For multiples of three print Fizz instead of the number and for multiples of five print Buzz.
For numbers which are multiples of both three and five print FizzBuzz.
Prototype: def fizzbuzz():
Each element should be followed by a space
You are not allowed to import any module
You don’t need to understand __import__

guillaume@ubuntu:~/0x01$ cat 12-main.py
#!/usr/bin/env python3
fizzbuzz = __import__('12-fizzbuzz').fizzbuzz

fizzbuzz()
print("")

guillaume@ubuntu:~/0x01$ ./12-main.py | cat -e
1 2 Fizz 4 Buzz Fizz 7 8 Fizz Buzz 11 Fizz 13 14 FizzBuzz 16 17 Fizz 19 Buzz Fizz 22 23 Fizz Buzz 26 Fizz 28 29 
FizzBuzz 31 32 Fizz 34 Buzz Fizz 37 38 Fizz Buzz 41 Fizz 43 44 FizzBuzz 46 47 Fizz 49 Buzz Fizz 52 53 Fizz Buzz 
56 Fizz 58 59 FizzBuzz 61 62 Fizz 64 Buzz Fizz 67 68 Fizz Buzz 71 Fizz 73 74 FizzBuzz 76 77 Fizz 79 Buzz Fizz 82 
83 Fizz Buzz 86 Fizz 88 89 FizzBuzz 91 92 Fizz 94 Buzz Fizz 97 98 Fizz Buzz $
guillaume@ubuntu:~/0x01$ 
Repo:

GitHub repository: alx-higher_level_programming
Directory: 0x01-python-if_else_loops_functions
File: 12-fizzbuzz.py

++++++++++++++++++++++++++++++++++++++++++++++++++++++++++++++++++++++++++++++++++++++++++++++++++++++++++++++++++

13. Insert in sorted linked list
mandatory
Technical interview preparation:

You are not allowed to google anything
Whiteboard first
Write a function in C that inserts a number into a sorted singly linked list.

Prototype: listint_t *insert_node(listint_t **head, int number);
Return: the address of the new node, or NULL if it failed
carrie@ubuntu:0x01$ cat lists.h 
#ifndef LISTS_H
#define LISTS_H

/**
 * struct listint_s - singly linked list
 * @n: integer
 * @next: points to the next node
 *
 * Description: singly linked list node structure
 *
 */
typedef struct listint_s
{
    int n;
    struct listint_s *next;
} listint_t;

size_t print_listint(const listint_t *h);
listint_t *add_nodeint_end(listint_t **head, const int n);
void free_listint(listint_t *head);

listint_t *insert_node(listint_t **head, int number);

#endif /* LISTS_H */
carrie@ubuntu:0x01$ cat linked_lists.c 
#include <stdio.h>
#include <stdlib.h>
#include "lists.h"

/**
 * print_listint - prints all elements of a listint_t list
 * @h: pointer to head of list
 * Return: number of nodes
 */
size_t print_listint(const listint_t *h)
{
    const listint_t *current;
    unsigned int n; /* number of nodes */

    current = h;
    n = 0;
    while (current != NULL)
    {
        printf("%i\n", current->n);
        current = current->next;
        n++;
    }

    return (n);
}

/**
 * add_nodeint_end - adds a new node at the end of a listint_t list
 * @head: pointer to pointer of first node of listint_t list
 * @n: integer to be included in new node
 * Return: address of the new element or NULL if it fails
 */
listint_t *add_nodeint_end(listint_t **head, const int n)
{
    listint_t *new;
    listint_t *current;

    current = *head;

    new = malloc(sizeof(listint_t));
    if (new == NULL)
        return (NULL);

    new->n = n;
    new->next = NULL;

    if (*head == NULL)
        *head = new;
    else
    {
        while (current->next != NULL)
            current = current->next;
        current->next = new;
    }

    return (new);
}

/**
 * free_listint - frees a listint_t list
 * @head: pointer to list to be freed
 * Return: void
 */
void free_listint(listint_t *head)
{
    listint_t *current;

    while (head != NULL)
    {
        current = head;
        head = head->next;
        free(current);
    }
}
carrie@ubuntu:0x01$ cat 13-main.c 
#include <stdlib.h>
#include <string.h>
#include <stdio.h>
#include "lists.h"

/**
 * main - check the code for
 *
 * Return: Always 0.
 */
int main(void)
{
    listint_t *head;

    head = NULL;
    add_nodeint_end(&head, 0);
    add_nodeint_end(&head, 1);
    add_nodeint_end(&head, 2);
    add_nodeint_end(&head, 3);
    add_nodeint_end(&head, 4);
    add_nodeint_end(&head, 98);
    add_nodeint_end(&head, 402);
    add_nodeint_end(&head, 1024);
    print_listint(head);

    printf("-----------------\n");

    insert_node(&head, 27);

    print_listint(head);

    free_listint(head);

    return (0);
}
carrie@ubuntu:0x01$ gcc -Wall -Werror -Wextra -pedantic -std=gnu89 13-main.c linked_lists.c 13-insert_number.c -o insert
carrie@ubuntu:0x01$ ./insert
0
1
2
3
4
98
402
1024
-----------------
0
1
2
3
4
27
98
402
1024
carrie@ubuntu:0x01$  
Repo:

GitHub repository: alx-higher_level_programming
Directory: 0x01-python-if_else_loops_functions
File: 13-insert_number.c, lists.h

+++++++++++++++++++++++++++++++++++++++++++++++++++++++++++++++++++++++++++++++++++++++++++++++++++++++++++++++

14. Smile in the mirror
#advanced
Write a program that prints the ASCII alphabet, in reverse order, alternating lowercase and uppercase 
(z in lowercase and Y in uppercase) , not followed by a new line.

You can only use one print function with string format
You can only use one loop in your code
You are not allowed to store characters in a variable
You are not allowed to import any module
guillaume@ubuntu:~/0x01$ ./100-print_tebahpla.py
zYxWvUtSrQpOnMlKjIhGfEdCbAguillaume@ubuntu:~/0x01$
Repo:

GitHub repository: alx-higher_level_programming
Directory: 0x01-python-if_else_loops_functions
File: 100-print_tebahpla.py
  
+++++++++++++++++++++++++++++++++++++++++++++++++++++++++++++++++++++++++++++++++++++++++++++++++++++++++++++++++++

15. Remove at position
#advanced
Write a function that creates a copy of the string, removing the character at the position n (not the Python way, 
the “C array index”).

Prototype: def remove_char_at(str, n):
You are not allowed to import any module
You don’t need to understand __import__

guillaume@ubuntu:~/0x01$ cat 101-main.py
#!/usr/bin/env python3
remove_char_at = __import__('101-remove_char_at').remove_char_at

print(remove_char_at("Best School", 3))
print(remove_char_at("Chicago", 2))
print(remove_char_at("C is fun!", 0))
print(remove_char_at("School", 10))
print(remove_char_at("Python", -2))

guillaume@ubuntu:~/0x01$ ./101-main.py
Bes School
Chcago
 is fun!
School
Python
guillaume@ubuntu:~/0x01$ 
Repo:

GitHub repository: alx-higher_level_programming
Directory: 0x01-python-if_else_loops_functions
File: 101-remove_char_at.py
  
++++++++++++++++++++++++++++++++++++++++++++++++++++++++++++++++++++++++++++++++++++++++++++++++++++++++++++++++++++++++

16. ByteCode -> Python #2
#advanced
Write the Python function def magic_calculation(a, b, c): that does exactly the same as the following Python bytecode:

  3           0 LOAD_FAST                0 (a)
              3 LOAD_FAST                1 (b)
              6 COMPARE_OP               0 (<)
              9 POP_JUMP_IF_FALSE       16

  4          12 LOAD_FAST                2 (c)
             15 RETURN_VALUE

  5     >>   16 LOAD_FAST                2 (c)
             19 LOAD_FAST                1 (b)
             22 COMPARE_OP               4 (>)
             25 POP_JUMP_IF_FALSE       36

  6          28 LOAD_FAST                0 (a)
             31 LOAD_FAST                1 (b)
             34 BINARY_ADD
             35 RETURN_VALUE

  7     >>   36 LOAD_FAST                0 (a)
             39 LOAD_FAST                1 (b)
             42 BINARY_MULTIPLY
             43 LOAD_FAST                2 (c)
             46 BINARY_SUBTRACT
             47 RETURN_VALUE
tips - ByteCode

Repo:

GitHub repository: alx-higher_level_programming
Directory: 0x01-python-if_else_loops_functions
File: 102-magic_calculation.py