6. Coordinates of a square
mandatory
Écrivez une classe Square qui définit un carré par : (basé sur 5-square.py)

Attribut d'instance privée : taille :
propriété def size(self) : pour la récupérer
propriété setter def size(self, value): pour le définir:
size doit être un entier, sinon déclencher une exception TypeError avec
la taille du message doit être un entier
si la taille est inférieure à 0, déclenche une exception ValueError avec
la taille du message doit être >= 0
Attribut d'instance privée : position :
propriété def position(self) : pour la récupérer
propriété setter def position(self, value): pour le définir:
position doit être un tuple de 2 entiers positifs,
sinon lever une exception TypeError avec la position du message doit être un tuple
 de 2 entiers positifs
Instanciation avec taille facultative et optionnelle
position : def __init__(soi, taille=0, position=(0, 0)) :
Méthode d'instance publique : def area(self) : qui renvoie la zone carrée actuelle
Méthode d'instance publique : def my_print(self) : qui imprime en stdout le carré avec
le personnage #:
si size est égal à 0, affiche une ligne vide
la position doit être utilisée en utilisant l'espace - Ne remplissez pas les lignes en
espaces lorsque position[1] > 0
Vous n'êtes pas autorisé à importer un module



Write a class Square that defines a square by: (based on 5-square.py)

Private instance attribute: size:
property def size(self): to retrieve it
property setter def size(self, value): to set it:
size must be an integer, otherwise raise a TypeError exception with 
the message size must be an integer
if size is less than 0, raise a ValueError exception with 
the message size must be >= 0
Private instance attribute: position:
property def position(self): to retrieve it
property setter def position(self, value): to set it:
position must be a tuple of 2 positive integers, 
otherwise raise a TypeError exception with the message position must be a tuple
 of 2 positive integers
Instantiation with optional size and optional 
position: def __init__(self, size=0, position=(0, 0)):
Public instance method: def area(self): that returns the current square area
Public instance method: def my_print(self): that prints in stdout the square with 
the character #:
if size is equal to 0, print an empty line
position should be use by using space - Don’t fill lines by 
spaces when position[1] > 0
You are not allowed to import any module
guillaume@ubuntu:~/0x06$ cat 6-main.py
#!/usr/bin/python3
Square = __import__('6-square').Square

my_square_1 = Square(3)
my_square_1.my_print()

print("--")

my_square_2 = Square(3, (1, 1))
my_square_2.my_print()

print("--")

my_square_3 = Square(3, (3, 0))
my_square_3.my_print()

print("--")

guillaume@ubuntu:~/0x06$ ./6-main.py | tr " " "_" | cat -e
###$
###$
###$
--$
$
_###$
_###$
_###$
--$
___###$
___###$
___###$
--$
guillaume@ubuntu:~/0x06$ 
Repo:

GitHub repository: alx-higher_level_programming
Directory: 0x06-python-classes
File: 6-square.py
   
7. Singly linked list
#advanced
Écrivez une classe Node qui définit un nœud d'une liste chaînée par :

Attribut d'instance privée : données :
propriété def data(self) : pour la récupérer
propriété setter def data(self, value): pour le définir:
les données doivent être un entier, sinon déclenchez une exception TypeError avec
les données du message doivent être un entier
Attribut d'instance privée : next_node :
property def next_node(self) : pour le récupérer
property setter def next_node(self, value): pour le définir :
next_node peut être None ou doit être un Node, sinon déclencher une exception TypeError
avec le message next_node doit être un objet Node
Instanciation avec data et next_node : def __init__(self, data, next_node=None) :
Et, écrivez une classe SinglyLinkedList qui définit une liste chaînée par :

Attribut d'instance privée : head (pas de setter ni de getter)
Instanciation simple : def __init__(self) :
Doit être imprimable :
imprimer toute la liste dans stdout
un numéro de nœud par ligne
Méthode d'instance publique : def sorted_insert(self, value) : qui insère un
nouveau nœud dans la bonne position triée dans la liste (ordre croissant)
Vous n'êtes pas autorisé à importer un module



Write a class Node that defines a node of a singly linked list by:

Private instance attribute: data:
property def data(self): to retrieve it
property setter def data(self, value): to set it:
data must be an integer, otherwise raise a TypeError exception with 
the message data must be an integer
Private instance attribute: next_node:
property def next_node(self): to retrieve it
property setter def next_node(self, value): to set it:
next_node can be None or must be a Node, otherwise raise a TypeError exception 
with the message next_node must be a Node object
Instantiation with data and next_node: def __init__(self, data, next_node=None):
And, write a class SinglyLinkedList that defines a singly linked list by:

Private instance attribute: head (no setter or getter)
Simple instantiation: def __init__(self):
Should be printable:
print the entire list in stdout
one node number by line
Public instance method: def sorted_insert(self, value): that inserts a 
new Node into the correct sorted position in the list (increasing order)
You are not allowed to import any module
guillaume@ubuntu:~/0x06$ cat 100-main.py
#!/usr/bin/python3
SinglyLinkedList = __import__('100-singly_linked_list').SinglyLinkedList

sll = SinglyLinkedList()
sll.sorted_insert(2)
sll.sorted_insert(5)
sll.sorted_insert(3)
sll.sorted_insert(10)
sll.sorted_insert(1)
sll.sorted_insert(-4)
sll.sorted_insert(-3)
sll.sorted_insert(4)
sll.sorted_insert(5)
sll.sorted_insert(12)
sll.sorted_insert(3)
print(sll)

guillaume@ubuntu:~/0x06$ ./100-main.py
-4
-3
1
2
3
3
4
5
5
10
12
guillaume@ubuntu:~/0x06$ 
Repo:

GitHub repository: alx-higher_level_programming
Directory: 0x06-python-classes
File: 100-singly_linked_list.py
   
8. Print Square instance
#advanced
Écrivez une classe Square qui définit un carré par : (basé sur 6-square.py)

Attribut d'instance privée : taille :
propriété def size(self) : pour la récupérer
propriété setter def size(self, value): pour le définir:
size doit être un entier, sinon déclencher une exception TypeError avec
la taille du message doit être un entier
si la taille est inférieure à 0, déclenche une exception ValueError avec
la taille du message doit être >= 0
Attribut d'instance privée : position :
propriété def position(self) : pour la récupérer
propriété setter def position(self, value): pour le définir:
position doit être un tuple de 2 entiers positifs,
sinon lever une exception TypeError avec la position du message doit être un tuple
de 2 entier positif
Instanciation avec taille facultative et optionnelle
position : def __init__(soi, taille=0, position=(0, 0)) :
Méthode d'instance publique : def area(self) : qui renvoie la zone carrée actuelle
Méthode d'instance publique : def my_print(self) :
qui imprime en stdout le carré avec le caractère # :
si size est égal à 0, affiche une ligne vide
la position doit être utilisée en utilisant l'espace
L'impression d'une instance Square devrait avoir le même comportement que my_print()
Vous n'êtes pas autorisé à importer un module



Write a class Square that defines a square by: (based on 6-square.py)

Private instance attribute: size:
property def size(self): to retrieve it
property setter def size(self, value): to set it:
size must be an integer, otherwise raise a TypeError exception with 
the message size must be an integer
if size is less than 0, raise a ValueError exception with 
the message size must be >= 0
Private instance attribute: position:
property def position(self): to retrieve it
property setter def position(self, value): to set it:
position must be a tuple of 2 positive integers, 
otherwise raise a TypeError exception with the message position must be a tuple 
of 2 positive integer
Instantiation with optional size and optional 
position: def __init__(self, size=0, position=(0, 0)):
Public instance method: def area(self): that returns the current square area
Public instance method: def my_print(self): 
that prints in stdout the square with the character #:
if size is equal to 0, print an empty line
position should be use by using space
Printing a Square instance should have the same behavior as my_print()
You are not allowed to import any module
guillaume@ubuntu:~/0x06$ cat 101-main.py
#!/usr/bin/python3
Square = __import__('101-square').Square

my_square = Square(5, (0, 0))
print(my_square)

print("--")

my_square = Square(5, (4, 1))
print(my_square)

guillaume@ubuntu:~/0x06$ ./101-main.py | tr " " "_" | cat -e
#####$
#####$
#####$
#####$
#####$
--$
$
____#####$
____#####$
____#####$
____#####$
____#####$
guillaume@ubuntu:~/0x06$ 
Repo:

GitHub repository: alx-higher_level_programming
Directory: 0x06-python-classes
File: 101-square.py
   
9. Compare 2 squares
#advanced
Écrivez une classe Square qui définit un carré par : (basé sur 4-square.py)

Attribut d'instance privée : taille :
propriété def size(self) : pour la récupérer
propriété setter def size(self, value): pour le définir:
size doit être un nombre (float ou entier), sinon déclencher une exception TypeError
avec la taille du message doit être un nombre
si la taille est inférieure à 0, déclenche une exception ValueError avec
la taille du message doit être >= 0
Instanciation avec taille : def __init__(self, size=0) :
Méthode d'instance publique : def area(self) : qui renvoie la zone carrée actuelle
L'instance carrée peut répondre aux comparateurs :
==, !=, >, >=, < et <= basés sur la surface carrée
Vous n'êtes pas autorisé à importer un module



Write a class Square that defines a square by: (based on 4-square.py)

Private instance attribute: size:
property def size(self): to retrieve it
property setter def size(self, value): to set it:
size must be a number (float or integer), otherwise raise a TypeError exception 
with the message size must be a number
if size is less than 0, raise a ValueError exception with 
the message size must be >= 0
Instantiation with size: def __init__(self, size=0):
Public instance method: def area(self): that returns the current square area
Square instance can answer to comparators: 
==, !=, >, >=, < and <= based on the square area
You are not allowed to import any module
guillaume@ubuntu:~/0x06$ cat 102-main.py
#!/usr/bin/python3
Square = __import__('102-square').Square

s_5 = Square(5)
s_6 = Square(6)

if s_5 < s_6:
    print("Square 5 < Square 6")
if s_5 <= s_6:
    print("Square 5 <= Square 6")
if s_5 == s_6:
    print("Square 5 == Square 6")
if s_5 != s_6:
    print("Square 5 != Square 6")
if s_5 > s_6:
    print("Square 5 > Square 6")
if s_5 >= s_6:
    print("Square 5 >= Square 6")

guillaume@ubuntu:~/0x06$ ./102-main.py
Square 5 < Square 6
Square 5 <= Square 6
Square 5 != Square 6
guillaume@ubuntu:~/0x06$ 
Repo:

GitHub repository: alx-higher_level_programming
Directory: 0x06-python-classes
File: 102-square.py
   
10. ByteCode -> Python #5
#advanced
Write the Python class MagicClass that does exactly the same as the following 
Python bytecode:

Disassembly of __init__:
 10           0 LOAD_CONST               1 (0)
              3 LOAD_FAST                0 (self)
              6 STORE_ATTR               0 (_MagicClass__radius)

 11           9 LOAD_GLOBAL              1 (type)
             12 LOAD_FAST                1 (radius)
             15 CALL_FUNCTION            1 (1 positional, 0 keyword pair)
             18 LOAD_GLOBAL              2 (int)
             21 COMPARE_OP               9 (is not)
             24 POP_JUMP_IF_FALSE       60
             27 LOAD_GLOBAL              1 (type)
             30 LOAD_FAST                1 (radius)
             33 CALL_FUNCTION            1 (1 positional, 0 keyword pair)
             36 LOAD_GLOBAL              3 (float)
             39 COMPARE_OP               9 (is not)
             42 POP_JUMP_IF_FALSE       60

 12          45 LOAD_GLOBAL              4 (TypeError)
             48 LOAD_CONST               2 ('radius must be a number')
             51 CALL_FUNCTION            1 (1 positional, 0 keyword pair)
             54 RAISE_VARARGS            1
             57 JUMP_FORWARD             0 (to 60)

 13     >>   60 LOAD_FAST                1 (radius)
             63 LOAD_FAST                0 (self)
             66 STORE_ATTR               0 (_MagicClass__radius)
             69 LOAD_CONST               3 (None)
             72 RETURN_VALUE

Disassembly of area:
 17           0 LOAD_FAST                0 (self)
              3 LOAD_ATTR                0 (_MagicClass__radius)
              6 LOAD_CONST               1 (2)
              9 BINARY_POWER
             10 LOAD_GLOBAL              1 (math)
             13 LOAD_ATTR                2 (pi)
             16 BINARY_MULTIPLY
             17 RETURN_VALUE

Disassembly of circumference:
 21           0 LOAD_CONST               1 (2)
              3 LOAD_GLOBAL              0 (math)
              6 LOAD_ATTR                1 (pi)
              9 BINARY_MULTIPLY
             10 LOAD_FAST                0 (self)
             13 LOAD_ATTR                2 (_MagicClass__radius)
             16 BINARY_MULTIPLY
             17 RETURN_VALUE
Tip: Python bytecode
Repo:

GitHub repository: alx-higher_level_programming
Directory: 0x06-python-classes
File: 103-magic_class.py