7. Easy print
#advanced
Écrivez un programme qui affiche #pythoniscool, suivi d'une nouvelle ligne, dans la sortie standard.

Votre programme doit faire au maximum 2 lignes
Vous n'êtes pas autorisé à utiliser print ou eval ou ouvrir ou importer sys dans votre fichier 101-easy_print.py


Write a program that prints #pythoniscool, followed by a new line, in the standard output.

Your program should be maximum 2 lines long
You are not allowed to use print or eval or open or import sys in your file 101-easy_print.py
guillaume@ubuntu:~/0x02$ ./101-easy_print.py
#pythoniscool
guillaume@ubuntu:~/0x02$ 
Repo:

GitHub repository: alx-higher_level_programming
Directory: 0x02-python-import_modules
File: 101-easy_print.py
/////////////////////////////////////////////////////////////////////////////////////////////////////////////////////////
8. ByteCode -> Python #3
#advanced
Write the Python function def magic_calculation(a, b): that does exactly the same as the following Python bytecode:

  3           0 LOAD_CONST               1 (0)
              3 LOAD_CONST               2 (('add', 'sub'))
              6 IMPORT_NAME              0 (magic_calculation_102)
              9 IMPORT_FROM              1 (add)
             12 STORE_FAST               2 (add)
             15 IMPORT_FROM              2 (sub)
             18 STORE_FAST               3 (sub)
             21 POP_TOP

  4          22 LOAD_FAST                0 (a)
             25 LOAD_FAST                1 (b)
             28 COMPARE_OP               0 (<)
             31 POP_JUMP_IF_FALSE       94

  5          34 LOAD_FAST                2 (add)
             37 LOAD_FAST                0 (a)
             40 LOAD_FAST                1 (b)
             43 CALL_FUNCTION            2 (2 positional, 0 keyword pair)
             46 STORE_FAST               4 (c)

  6          49 SETUP_LOOP              38 (to 90)
             52 LOAD_GLOBAL              3 (range)
             55 LOAD_CONST               3 (4)
             58 LOAD_CONST               4 (6)
             61 CALL_FUNCTION            2 (2 positional, 0 keyword pair)
             64 GET_ITER
        >>   65 FOR_ITER                21 (to 89)
             68 STORE_FAST               5 (i)

  7          71 LOAD_FAST                2 (add)
             74 LOAD_FAST                4 (c)
             77 LOAD_FAST                5 (i)
             80 CALL_FUNCTION            2 (2 positional, 0 keyword pair)
             83 STORE_FAST               4 (c)
             86 JUMP_ABSOLUTE           65
        >>   89 POP_BLOCK

  8     >>   90 LOAD_FAST                4 (c)
             93 RETURN_VALUE

 10     >>   94 LOAD_FAST                3 (sub)
             97 LOAD_FAST                0 (a)
            100 LOAD_FAST                1 (b)
            103 CALL_FUNCTION            2 (2 positional, 0 keyword pair)
            106 RETURN_VALUE
            107 LOAD_CONST               0 (None)
            110 RETURN_VALUE
Tip: Python bytecode
Repo:

GitHub repository: alx-higher_level_programming
Directory: 0x02-python-import_modules
File: 102-magic_calculation.py
/////////////////////////////////////////////////////////////////////////////////////////////////////////////////////
9. Fast alphabet
#advanced
Écrivez un programme qui imprime l'alphabet en majuscule, suivi d'une nouvelle ligne.

Votre programme doit faire au maximum 3 lignes
Vous n'êtes pas autorisé à utiliser :
toutes les boucles
toutes les instructions conditionnelles
str.join()
n'importe quel littéral de chaîne
tous les appels système


Write a program that prints the alphabet in uppercase, followed by a new line.

Your program should be maximum 3 lines long
You are not allowed to use:
any loops
any conditional statements
str.join()
any string literal
any system calls
guillaume@ubuntu:~/0x02$ ./103-fast_alphabet.py
ABCDEFGHIJKLMNOPQRSTUVWXYZ
guillaume@ubuntu:~/0x02$ wc -l 103-fast_alphabet.py
3 103-fast_alphabet.py
guillaume@ubuntu:~/0x02$
Repo:

GitHub repository: alx-higher_level_programming
Directory: 0x02-python-import_modules
File: 103-fast_alphabet.py