5. Raise exception
mandatory
Écrivez une fonction qui lève une exception de type.

Prototype : def raise_exception() :
Vous n'êtes pas autorisé à importer un module


Write a function that raises a type exception.

Prototype: def raise_exception():
You are not allowed to import any module
guillaume@ubuntu:~/0x05$ cat 5-main.py
#!/usr/bin/python3
raise_exception = __import__('5-raise_exception').raise_exception

try:
    raise_exception()
except TypeError as te:
    print("Exception raised")

guillaume@ubuntu:~/0x05$ ./5-main.py
Exception raised
guillaume@ubuntu:~/0x05$ 
Repo:

GitHub repository: alx-higher_level_programming
Directory: 0x05-python-exceptions
File: 5-raise_exception.py
####################################################################################
6. Raise a message
mandatory
Écrivez une fonction qui déclenche une exception de nom avec un message.

Prototype : def raise_exception_msg(message="") :
Vous n'êtes pas autorisé à importer un module


Write a function that raises a name exception with a message.

Prototype: def raise_exception_msg(message=""):
You are not allowed to import any module
guillaume@ubuntu:~/0x05$ cat 6-main.py
#!/usr/bin/python3
raise_exception_msg = __import__('6-raise_exception_msg').raise_exception_msg

try:
    raise_exception_msg("C is fun")
except NameError as ne:
    print(ne)

guillaume@ubuntu:~/0x05$ ./6-main.py
C is fun
guillaume@ubuntu:~/0x05$ 
Repo:

GitHub repository: alx-higher_level_programming
Directory: 0x05-python-exceptions
File: 6-raise_exception_msg.py
####################################################################################
7. Safe integer print with error message
#advanced
Ecrire une fonction qui imprime un entier.

Prototype : def safe_print_integer_err(valeur) :
la valeur peut être de n'importe quel type (entier, chaîne, etc.)
L'entier doit être imprimé suivi d'une nouvelle ligne
Renvoie True si la valeur a été correctement imprimée 
(cela signifie que la valeur est un entier)
Sinon, renvoie False et imprime dans stderr l'erreur précédée d'Exception :
Vous devez utiliser try: / sauf:
Vous devez utiliser "{:d}".format() pour imprimer en entier
Vous n'êtes pas autorisé à utiliser type()


Write a function that prints an integer.

Prototype: def safe_print_integer_err(value):
value can be any type (integer, string, etc.)
The integer should be printed followed by a new line
Returns True if value has been correctly printed (it means the value is an integer)
Otherwise, returns False and prints in stderr the error precede by Exception:
You have to use try: / except:
You have to use "{:d}".format() to print as integer
You are not allowed to use type()
guillaume@ubuntu:~/0x05$ cat 100-main.py
#!/usr/bin/python3
safe_print_integer_err = \
    __import__('100-safe_print_integer_err').safe_print_integer_err

value = 89
has_been_print = safe_print_integer_err(value)
if not has_been_print:
    print("{} is not an integer".format(value))

value = -89
has_been_print = safe_print_integer_err(value)
if not has_been_print:
    print("{} is not an integer".format(value))

value = "School"
has_been_print = safe_print_integer_err(value)
if not has_been_print:
    print("{} is not an integer".format(value))

guillaume@ubuntu:~/0x05$ ./100-main.py
89
-89
Exception: Unknown format code 'd' for object of type 'str'
School is not an integer
guillaume@ubuntu:~/0x05$ ./100-main.py 2> /dev/null
89
-89
School is not an integer
guillaume@ubuntu:~/0x05$ 
Repo:

GitHub repository: alx-higher_level_programming
Directory: 0x05-python-exceptions
File: 100-safe_print_integer_err.py
####################################################################################
8. Safe function
#advanced
Écrivez une fonction qui exécute une fonction en toute sécurité.

Prototype : def safe_function(fct, *args) :
Vous pouvez supposer que fct sera toujours un pointeur vers une fonction
Renvoie le résultat de la fonction,
Sinon, renvoie None si quelque chose se passe pendant la fonction et
imprime dans stderr l'erreur précédée d'Exception :
Vous devez utiliser try: / sauf:


Write a function that executes a function safely.

Prototype: def safe_function(fct, *args):
You can assume fct will be always a pointer to a function
Returns the result of the function,
Otherwise, returns None if something happens during the function and 
prints in stderr the error precede by Exception:
You have to use try: / except:
guillaume@ubuntu:~/0x05$ cat 101-main.py
#!/usr/bin/python3
safe_function = __import__('101-safe_function').safe_function


def my_div(a, b):
    return a / b

result = safe_function(my_div, 10, 2)
print("result of my_div: {}".format(result))

result = safe_function(my_div, 10, 0)
print("result of my_div: {}".format(result))


def print_list(my_list, len):
    i = 0
    while i < len:
        print(my_list[i])
        i += 1
    return len

result = safe_function(print_list, [1, 2, 3, 4], 10)
print("result of print_list: {}".format(result))

guillaume@ubuntu:~/0x05$ ./101-main.py
result of my_div: 5.0
Exception: division by zero
result of my_div: None
1
2
3
4
Exception: list index out of range
result of print_list: None
guillaume@ubuntu:~/0x05$ ./101-main.py 2> /dev/null
result of my_div: 5.0
result of my_div: None
1
2
3
4
result of print_list: None
guillaume@ubuntu:~/0x05$ 
Repo:

GitHub repository: alx-higher_level_programming
Directory: 0x05-python-exceptions
File: 101-safe_function.py
####################################################################################
9. ByteCode -> Python #4
#advanced
Write the Python function def magic_calculation(a, b): 
that does exactly the same as the following Python bytecode:

  3           0 LOAD_CONST               1 (0)
              3 STORE_FAST               2 (result)

  4           6 SETUP_LOOP              94 (to 103)
              9 LOAD_GLOBAL              0 (range)
             12 LOAD_CONST               2 (1)
             15 LOAD_CONST               3 (3)
             18 CALL_FUNCTION            2 (2 positional, 0 keyword pair)
             21 GET_ITER
        >>   22 FOR_ITER                77 (to 102)
             25 STORE_FAST               3 (i)

  5          28 SETUP_EXCEPT            49 (to 80)

  6          31 LOAD_FAST                3 (i)
             34 LOAD_FAST                0 (a)
             37 COMPARE_OP               4 (>)
             40 POP_JUMP_IF_FALSE       58

  7          43 LOAD_GLOBAL              1 (Exception)
             46 LOAD_CONST               4 ('Too far')
             49 CALL_FUNCTION            1 (1 positional, 0 keyword pair)
             52 RAISE_VARARGS            1
             55 JUMP_FORWARD            18 (to 76)

  9     >>   58 LOAD_FAST                2 (result)
             61 LOAD_FAST                0 (a)
             64 LOAD_FAST                1 (b)
             67 BINARY_POWER
             68 LOAD_FAST                3 (i)
             71 BINARY_TRUE_DIVIDE
             72 INPLACE_ADD
             73 STORE_FAST               2 (result)
        >>   76 POP_BLOCK
             77 JUMP_ABSOLUTE           22

 10     >>   80 POP_TOP
             81 POP_TOP
             82 POP_TOP

 11          83 LOAD_FAST                1 (b)
             86 LOAD_FAST                0 (a)
             89 BINARY_ADD
             90 STORE_FAST               2 (result)

 12          93 BREAK_LOOP
             94 POP_EXCEPT
             95 JUMP_ABSOLUTE           22
             98 END_FINALLY
             99 JUMP_ABSOLUTE           22
        >>  102 POP_BLOCK

 13     >>  103 LOAD_FAST                2 (result)
            106 RETURN_VALUE
Tip: Python bytecode
Repo:

GitHub repository: alx-higher_level_programming
Directory: 0x05-python-exceptions
File: 102-magic_calculation.py
